xtellixClient/__init__.py
xtellixClient/griewank-example.py
xtellixClient/xtellixClient.py
xtellixClient-0.0.2.dist-info/LICENSE
xtellixClient-0.0.2.dist-info/METADATA
xtellixClient-0.0.2.dist-info/WHEEL
xtellixClient-0.0.2.dist-info/top_level.txt
xtellixClient-0.0.2.dist-info/RECORD
