Metadata-Version: 2.1
Name: xtellixClient
Version: 0.0.2
Summary: A Python Client for Connecting to xtellix Optimization Servers using REST API
Home-page: https://github.com/markamo/xtellixClient
Author: Dr Mark Amo-Boateng
Author-email: m.amoboateng@gmail.com
License: UNKNOWN
Platform: UNKNOWN
Classifier: Programming Language :: Python :: 3
Classifier: License :: OSI Approved :: MIT License
Classifier: Operating System :: OS Independent
Requires-Python: >=3.5
